[{"title":"Test Title","text":"Test text"},{"title":"sfvdf","text":"dfvdg","id":"b2e4"},{"title":"sfvsfv","text":"sfvsfv","id":"7bd1"},{"title":"fdhdfhg","text":"sdfgdfghd","id":"0c28"},{"title":"sdvcsd","text":"affcsd","id":"27c7"},{"title":"jgkfujk","text":"nvhmnuj","id":"7af4"},{"title":"kik","text":"rocs\n","date":"","id":"4a98"},{"title":"jmn","text":"mmmmm","id":"ebd4"},{"title":"gnvn","text":"vnmcnjmfghdhdfgffdffgcnfg","id":"918c"},{"title":"ngwqa","text":"azscxs","id":"406c"},{"title":"mugmjj","text":"mbjmb","id":"08eb"},{"title":"cdc","text":"bgnvb","id":"3d64"},{"title":"az","text":"az","id":"4f08"},{"title":"sash is gay","text":"gary is gayer","id":"8e47"},{"title":"Cheese Teeth","text":"Gary loves Havarti!!","id":"1b45"},{"title":"gg","text":"gg","id":"d42b"},{"title":"Hokaido","text":"hokaifdo","date":"2022-11-10T23:46","id":"65c1"},{"title":"tgdbg","text":"mnhbgfvc","date":"2022-11-12T23:59","id":"08f7"},{"title":"vfgdhb","text":"gbxgng","date":"2022-11-24T00:01","id":"de3f"},{"title":"gsrt","text":"thyd","date":"2022-11-24T00:04","id":"63c7"},{"title":"ergtrr","text":"hjch","date":"2022-11-23T00:09:40","id":"2ce8"},{"title":"halo","text":"halo","date":"2022-11-10T00:31:31","id":"be05"},{"title":"asdf","text":"fasdf","date":"2022-11-10T00:34:16","id":"0cb5"},{"title":"sfa","text":"asdf","date":"2022-11-10T00:35:24","id":"add5"},{"title":"sdf","text":"sdfs","date":"2022-11-10T00:36:54","id":"2636"},{"title":"fsdf","text":"ss","date":"2022-11-10T00:39:41","id":"c214"},{"title":"vcxzv","text":"vzxcv","date":"2022-11-10T00:50:12","id":"a7f2"},{"title":"sfsf","text":"sdfdfsdf","date":"2022-11-10T00:53:45","id":"cb6d"},{"title":"asdf","text":"fasdf","date":"2022-11-10T00:56","id":"7716"},{"title":"fvdfv","text":"sdfvdfv","date":"2022-11-10T17:53:17","id":"8118"},{"title":"sdcs","text":" x vf","date":"2022-11-10T18:06:46","id":"9f12"}]